{"source":"Ofsted state-funded schools management information (Apr 2026)","sourceUrl":"https://www.gov.uk/government/statistical-data-sets/monthly-management-information-ofsteds-school-inspections-outcomes","schools":[{"urn":140211,"name":"Berewood Primary School","type":"Primary","ofstedRating":"Good","postcode":"PO7 3BE","ageRange":"4-11","pupils":415},{"urn":116083,"name":"Castle Primary School","type":"Primary","ofstedRating":"Good","postcode":"PO16 9QQ","ageRange":"4-11","pupils":393},{"urn":115882,"name":"Denmead Infant School","type":"Primary","ofstedRating":"Good","postcode":"PO7 6PN","ageRange":"4-7","pupils":208},{"urn":116043,"name":"Denmead Junior School","type":"Primary","ofstedRating":"Not inspected","postcode":"PO7 6PH","ageRange":"7-11","pupils":336},{"urn":115990,"name":"Harrison Primary School","type":"Primary","ofstedRating":"Outstanding","postcode":"PO16 7EQ","ageRange":"4-11","pupils":614},{"urn":115966,"name":"Hart Plain Infant School","type":"Primary","ofstedRating":"Good","postcode":"PO8 8RZ","ageRange":"4-7","pupils":130},{"urn":116244,"name":"Hart Plain Junior School","type":"Primary","ofstedRating":"Not inspected","postcode":"PO8 8SA","ageRange":"7-11","pupils":211},{"urn":151648,"name":"Newlands Primary Academy","type":"Primary","ofstedRating":"Not inspected","postcode":"PO7 3FE","ageRange":"4-11","pupils":0},{"urn":116030,"name":"Northern Infant School","type":"Primary","ofstedRating":"Good","postcode":"PO16 8DG","ageRange":"5-7","pupils":138},{"urn":115935,"name":"Northern Junior School","type":"Primary","ofstedRating":"Good","postcode":"PO16 8DG","ageRange":"7-11","pupils":222},{"urn":116224,"name":"Orchard Lea Infant School","type":"Primary","ofstedRating":"Requires Improvement","postcode":"PO15 6BJ","ageRange":"4-7","pupils":132},{"urn":116225,"name":"Orchard Lea Junior School","type":"Primary","ofstedRating":"Good","postcode":"PO15 6BJ","ageRange":"7-11","pupils":223},{"urn":115965,"name":"Padnell Infant School","type":"Primary","ofstedRating":"Good","postcode":"PO8 8DS","ageRange":"4-7","pupils":269},{"urn":115964,"name":"Padnell Junior School","type":"Primary","ofstedRating":"Good","postcode":"PO8 8EA","ageRange":"7-11","pupils":361},{"urn":116248,"name":"Queen's Inclosure Primary School","type":"Primary","ofstedRating":"Good","postcode":"PO7 8NT","ageRange":"4-11","pupils":415},{"urn":116079,"name":"Red Barn Community Primary School","type":"Primary","ofstedRating":"Outstanding","postcode":"PO16 8HJ","ageRange":"4-11","pupils":211},{"urn":115892,"name":"Redlands Primary School","type":"Primary","ofstedRating":"Outstanding","postcode":"PO16 0UD","ageRange":"4-11","pupils":313},{"urn":147701,"name":"St Columba CE Primary School","type":"Primary","ofstedRating":"Good","postcode":"PO15 6LL","ageRange":"4-11","pupils":89},{"urn":116376,"name":"St Jude's Catholic Primary School","type":"Primary","ofstedRating":"Not inspected","postcode":"PO14 1ND","ageRange":"3-11","pupils":221},{"urn":115890,"name":"Uplands Primary School","type":"Primary","ofstedRating":"Good","postcode":"PO16 7QP","ageRange":"4-11","pupils":310},{"urn":115893,"name":"Wallisdean Infant School","type":"Primary","ofstedRating":"Not inspected","postcode":"PO14 1HT","ageRange":"3-7","pupils":156},{"urn":115889,"name":"Wallisdean Junior School","type":"Primary","ofstedRating":"Good","postcode":"PO14 1HU","ageRange":"7-11","pupils":218},{"urn":116325,"name":"Wickham Church of England Primary School","type":"Primary","ofstedRating":"Good","postcode":"PO17 5HU","ageRange":"4-11","pupils":289},{"urn":115938,"name":"Wicor Primary School","type":"Primary","ofstedRating":"Not inspected","postcode":"PO16 9DL","ageRange":"4-11","pupils":428},{"urn":135529,"name":"Woodcroft Primary","type":"Primary","ofstedRating":"Good","postcode":"PO8 9QD","ageRange":"4-11","pupils":197},{"urn":137538,"name":"Cams Hill School","type":"Secondary","ofstedRating":"Good","postcode":"PO16 8AH","ageRange":"11-16","pupils":1237},{"urn":140069,"name":"Fareham Academy","type":"Secondary","ofstedRating":"Good","postcode":"PO14 1JJ","ageRange":"11-16","pupils":884},{"urn":116418,"name":"Portchester Community School","type":"Secondary","ofstedRating":"Good","postcode":"PO16 9BD","ageRange":"11-16","pupils":692},{"urn":138038,"name":"The Cowplain School","type":"Secondary","ofstedRating":"Good","postcode":"PO8 8RY","ageRange":"11-16","pupils":1011},{"urn":116466,"name":"The Henry Cort Community College","type":"Secondary","ofstedRating":"Requires Improvement","postcode":"PO15 6PH","ageRange":"11-16","pupils":856},{"urn":116611,"name":"Rachel Madocks School","type":"Special","ofstedRating":"Good","postcode":"PO8 9XP","ageRange":"2-19","pupils":102},{"urn":116633,"name":"The Waterloo School","type":"Special","ofstedRating":"Not inspected","postcode":"PO7 7JJ","ageRange":"5-11","pupils":75}]}