{"source":"Ofsted state-funded schools management information (Apr 2026)","sourceUrl":"https://www.gov.uk/government/statistical-data-sets/monthly-management-information-ofsteds-school-inspections-outcomes","schools":[{"urn":145142,"name":"Avanti House Primary School","type":"Primary","ofstedRating":"Good","postcode":"HA7 3JB","ageRange":"4-11","pupils":419},{"urn":140657,"name":"Aylward Primary School","type":"Primary","ofstedRating":"Good","postcode":"HA7 4RE","ageRange":"3-11","pupils":537},{"urn":102188,"name":"Camrose Primary With Nursery","type":"Primary","ofstedRating":"Good","postcode":"HA8 6JH","ageRange":"3-11","pupils":423},{"urn":135211,"name":"Cedars Manor School","type":"Primary","ofstedRating":"Good","postcode":"HA3 6LS","ageRange":"3-11","pupils":388},{"urn":102211,"name":"Elmgrove Primary School & Nursery","type":"Primary","ofstedRating":"Good","postcode":"HA3 8LU","ageRange":"3-11","pupils":802},{"urn":102224,"name":"Glebe Primary School","type":"Primary","ofstedRating":"Requires Improvement","postcode":"HA3 9LF","ageRange":"3-11","pupils":580},{"urn":143925,"name":"Hujjat Primary School","type":"Primary","ofstedRating":"Good","postcode":"HA3 6RR","ageRange":"4-11","pupils":296},{"urn":102212,"name":"Kenmore Park Infant and Nursery School","type":"Primary","ofstedRating":"Good","postcode":"HA3 9JA","ageRange":"3-7","pupils":297},{"urn":102193,"name":"Kenmore Park Junior School","type":"Primary","ofstedRating":"Good","postcode":"HA3 9JA","ageRange":"7-11","pupils":323},{"urn":101503,"name":"Kingsbury Green Primary School","type":"Primary","ofstedRating":"Good","postcode":"NW9 9ND","ageRange":"3-11","pupils":573},{"urn":138688,"name":"Krishna Avanti Primary School","type":"Primary","ofstedRating":"Good","postcode":"HA8 6ES","ageRange":"3-11","pupils":454},{"urn":146750,"name":"Priestmead Primary School and Nursery","type":"Primary","ofstedRating":"Outstanding","postcode":"HA3 8SZ","ageRange":"3-11","pupils":880},{"urn":101512,"name":"Roe Green Infant School","type":"Primary","ofstedRating":"Good","postcode":"NW9 9JL","ageRange":"3-7","pupils":437},{"urn":101511,"name":"Roe Green Junior School","type":"Primary","ofstedRating":"Good","postcode":"NW9 9JL","ageRange":"7-11","pupils":476},{"urn":142558,"name":"St Bernadette's Catholic Primary School","type":"Primary","ofstedRating":"Not inspected","postcode":"HA3 9NS","ageRange":"3-11","pupils":450},{"urn":134929,"name":"St John's CofE School","type":"Primary","ofstedRating":"Good","postcode":"HA7 3FD","ageRange":"3-11","pupils":280},{"urn":146246,"name":"St Joseph's Catholic Primary School","type":"Primary","ofstedRating":"Good","postcode":"HA3 7LP","ageRange":"3-11","pupils":408},{"urn":102209,"name":"Stag Lane Primary School","type":"Primary","ofstedRating":"Not inspected","postcode":"HA8 5RU","ageRange":"3-11","pupils":874},{"urn":102214,"name":"Stanburn Primary School","type":"Primary","ofstedRating":"Good","postcode":"HA7 2PJ","ageRange":"3-11","pupils":676},{"urn":102215,"name":"Weald Rise Primary School","type":"Primary","ofstedRating":"Good","postcode":"HA3 7DH","ageRange":"2-11","pupils":380},{"urn":131316,"name":"Whitchurch Primary School & Nursery","type":"Primary","ofstedRating":"Good","postcode":"HA7 2EQ","ageRange":"3-11","pupils":845},{"urn":138227,"name":"Avanti House School","type":"Secondary","ofstedRating":"Good","postcode":"HA7 2EQ","ageRange":"11-18","pupils":1182},{"urn":137178,"name":"Bentley Wood High School","type":"Secondary","ofstedRating":"Outstanding","postcode":"HA7 3JW","ageRange":"11-18","pupils":1394},{"urn":137199,"name":"Canons High School","type":"Secondary","ofstedRating":"Good","postcode":"HA8 6AN","ageRange":"11-18","pupils":1217},{"urn":137685,"name":"Kingsbury High School","type":"Secondary","ofstedRating":"Good","postcode":"NW9 9JR","ageRange":"11-18","pupils":1997},{"urn":137075,"name":"Park High School","type":"Secondary","ofstedRating":"Not inspected","postcode":"HA7 1PL","ageRange":"11-18","pupils":1471},{"urn":133317,"name":"Kingsley High School","type":"Special","ofstedRating":"Outstanding","postcode":"HA3 6ND","ageRange":"11-19","pupils":129},{"urn":102180,"name":"The Helix Education Centre","type":"Special","ofstedRating":"Good","postcode":"HA3 6DH","ageRange":"5-16","pupils":36},{"urn":133316,"name":"Woodlands School","type":"Special","ofstedRating":"Outstanding","postcode":"HA8 6JP","ageRange":"4-11","pupils":137}]}