{"source":"Ofsted state-funded schools management information (Apr 2026)","sourceUrl":"https://www.gov.uk/government/statistical-data-sets/monthly-management-information-ofsteds-school-inspections-outcomes","schools":[{"urn":143130,"name":"OA - Havering","type":"Other","ofstedRating":"Good","postcode":"RM11 3UR","ageRange":"7-16","pupils":33},{"urn":135588,"name":"Branfil Primary School","type":"Primary","ofstedRating":"Good","postcode":"RM14 2LW","ageRange":"4-11","pupils":554},{"urn":102317,"name":"Broadford Primary School","type":"Primary","ofstedRating":"Good","postcode":"RM3 8JS","ageRange":"3-11","pupils":670},{"urn":142966,"name":"Drapers' Brookside Infant School","type":"Primary","ofstedRating":"Good","postcode":"RM3 9DJ","ageRange":"3-7","pupils":229},{"urn":140818,"name":"Drapers' Brookside Junior School","type":"Primary","ofstedRating":"Good","postcode":"RM3 9DJ","ageRange":"7-11","pupils":238},{"urn":141549,"name":"Drapers' Maylands Primary School","type":"Primary","ofstedRating":"Good","postcode":"RM3 9XR","ageRange":"3-11","pupils":361},{"urn":141577,"name":"Drapers' Pyrgo Priory School","type":"Primary","ofstedRating":"Not inspected","postcode":"RM3 9RT","ageRange":"3-11","pupils":320},{"urn":132766,"name":"Engayne Primary School","type":"Primary","ofstedRating":"Good","postcode":"RM14 1SW","ageRange":"5-11","pupils":587},{"urn":146136,"name":"Hacton Primary School","type":"Primary","ofstedRating":"Outstanding","postcode":"RM12 6AU","ageRange":"3-11","pupils":635},{"urn":102278,"name":"Harold Court Primary School","type":"Primary","ofstedRating":"Good","postcode":"RM3 0SH","ageRange":"3-11","pupils":386},{"urn":102269,"name":"Harold Wood Primary School","type":"Primary","ofstedRating":"Not inspected","postcode":"RM3 0TH","ageRange":"4-11","pupils":641},{"urn":102325,"name":"Hilldene Primary School","type":"Primary","ofstedRating":"Not inspected","postcode":"RM3 7DU","ageRange":"3-11","pupils":663},{"urn":102280,"name":"Langtons Infant School & Nursery","type":"Primary","ofstedRating":"Good","postcode":"RM11 3SD","ageRange":"3-7","pupils":198},{"urn":139406,"name":"Langtons Junior Academy","type":"Primary","ofstedRating":"Good","postcode":"RM11 3SD","ageRange":"7-11","pupils":221},{"urn":102322,"name":"Mead Primary School","type":"Primary","ofstedRating":"Good","postcode":"RM3 9JD","ageRange":"3-11","pupils":796},{"urn":102321,"name":"Nelmes Primary School","type":"Primary","ofstedRating":"Not inspected","postcode":"RM11 3BX","ageRange":"4-11","pupils":430},{"urn":102316,"name":"Scotts Primary School","type":"Primary","ofstedRating":"Outstanding","postcode":"RM12 6TH","ageRange":"4-11","pupils":420},{"urn":102334,"name":"St Joseph's Catholic Primary School","type":"Primary","ofstedRating":"Good","postcode":"RM14 2QB","ageRange":"4-11","pupils":411},{"urn":102332,"name":"St Ursula's Catholic Primary School","type":"Primary","ofstedRating":"Good","postcode":"RM3 7JS","ageRange":"3-11","pupils":439},{"urn":102283,"name":"Suttons Primary School","type":"Primary","ofstedRating":"Good","postcode":"RM12 6RP","ageRange":"2-11","pupils":466},{"urn":102268,"name":"The James Oglethorpe Primary School","type":"Primary","ofstedRating":"Good","postcode":"RM14 3NB","ageRange":"4-11","pupils":396},{"urn":138943,"name":"Upminster Infant School","type":"Primary","ofstedRating":"Good","postcode":"RM14 3BS","ageRange":"5-7","pupils":267},{"urn":138944,"name":"Upminster Junior School","type":"Primary","ofstedRating":"Good","postcode":"RM14 3BS","ageRange":"7-11","pupils":362},{"urn":136663,"name":"Abbs Cross Academy and Arts College","type":"Secondary","ofstedRating":"Good","postcode":"RM12 4YB","ageRange":"11-16","pupils":887},{"urn":136090,"name":"Drapers' Academy","type":"Secondary","ofstedRating":"Not inspected","postcode":"RM3 9XR","ageRange":"11-18","pupils":1206},{"urn":137414,"name":"Emerson Park Academy","type":"Secondary","ofstedRating":"Good","postcode":"RM11 3AD","ageRange":"11-16","pupils":1034},{"urn":144095,"name":"Gaynes School","type":"Secondary","ofstedRating":"Good","postcode":"RM14 3UX","ageRange":"11-16","pupils":473},{"urn":137197,"name":"Hall Mead School","type":"Secondary","ofstedRating":"Outstanding","postcode":"RM14 1SF","ageRange":"11-16","pupils":1066},{"urn":137396,"name":"Redden Court School","type":"Secondary","ofstedRating":"Outstanding","postcode":"RM3 0TS","ageRange":"11-16","pupils":1061},{"urn":137233,"name":"Sacred Heart of Mary Girls' School","type":"Secondary","ofstedRating":"Not inspected","postcode":"RM14 2QR","ageRange":"11-18","pupils":829},{"urn":146309,"name":"Sanders Draper","type":"Secondary","ofstedRating":"Good","postcode":"RM12 6RT","ageRange":"11-16","pupils":705},{"urn":137040,"name":"The Campion School","type":"Secondary","ofstedRating":"Good","postcode":"RM11 3BX","ageRange":"11-18","pupils":1244},{"urn":136600,"name":"The Coopers' Company and Coborn School","type":"Secondary","ofstedRating":"Good","postcode":"RM14 3HS","ageRange":"11-18","pupils":1550},{"urn":102362,"name":"Corbets Tey School","type":"Special","ofstedRating":"Good","postcode":"RM14 2YQ","ageRange":"4-19","pupils":158},{"urn":142050,"name":"Lime Academy Forest Approach","type":"Special","ofstedRating":"Good","postcode":"RM3 9YA","ageRange":"2-19","pupils":129},{"urn":142722,"name":"Lime Academy Ravensbourne","type":"Special","ofstedRating":"Good","postcode":"RM3 8HN","ageRange":"2-19","pupils":86}]}