{"source":"Ofsted state-funded schools management information (Apr 2026)","sourceUrl":"https://www.gov.uk/government/statistical-data-sets/monthly-management-information-ofsteds-school-inspections-outcomes","schools":[{"urn":140656,"name":"Alston Primary School","type":"Primary","ofstedRating":"Not inspected","postcode":"B9 5UN","ageRange":"3-11","pupils":634},{"urn":143437,"name":"Audley Primary School","type":"Primary","ofstedRating":"Good","postcode":"B33 9HY","ageRange":"3-11","pupils":857},{"urn":103172,"name":"Bordesley Green Primary School","type":"Primary","ofstedRating":"Good","postcode":"B9 5XX","ageRange":"3-11","pupils":671},{"urn":141320,"name":"Brownmead Primary Academy","type":"Primary","ofstedRating":"Good","postcode":"B34 6SS","ageRange":"5-11","pupils":316},{"urn":149490,"name":"Castle Bromwich Infant and Nursery School","type":"Primary","ofstedRating":"Good","postcode":"B36 0BX","ageRange":"2-7","pupils":495},{"urn":149489,"name":"Castle Bromwich Junior School","type":"Primary","ofstedRating":"Good","postcode":"B36 0HD","ageRange":"7-11","pupils":465},{"urn":103263,"name":"Colebourne Primary School","type":"Primary","ofstedRating":"Not inspected","postcode":"B34 6BJ","ageRange":"3-11","pupils":451},{"urn":143089,"name":"Firs Primary School","type":"Primary","ofstedRating":"Requires Improvement","postcode":"B36 8LL","ageRange":"3-11","pupils":327},{"urn":142794,"name":"Gossey Lane Academy","type":"Primary","ofstedRating":"Not inspected","postcode":"B33 0DS","ageRange":"3-11","pupils":187},{"urn":148081,"name":"Guardian Angels Catholic Primary School","type":"Primary","ofstedRating":"Good","postcode":"B34 7HN","ageRange":"4-11","pupils":201},{"urn":140890,"name":"Heathlands Primary Academy","type":"Primary","ofstedRating":"Good","postcode":"B34 6NB","ageRange":"3-11","pupils":447},{"urn":141270,"name":"Hillstone Primary School","type":"Primary","ofstedRating":"Good","postcode":"B34 7PY","ageRange":"2-11","pupils":433},{"urn":143869,"name":"Hodge Hill Primary School","type":"Primary","ofstedRating":"Good","postcode":"B36 8LD","ageRange":"4-11","pupils":688},{"urn":151168,"name":"Kingshurst Primary School","type":"Primary","ofstedRating":"Requires Improvement","postcode":"B37 6BN","ageRange":"3-11","pupils":474},{"urn":140502,"name":"Leigh Primary School","type":"Primary","ofstedRating":"Good","postcode":"B8 2YH","ageRange":"3-11","pupils":425},{"urn":139003,"name":"Lift Lea Forest","type":"Primary","ofstedRating":"Outstanding","postcode":"B33 9RD","ageRange":"3-11","pupils":551},{"urn":139120,"name":"Oasis Academy Blakenhale Infants","type":"Primary","ofstedRating":"Good","postcode":"B33 0XD","ageRange":"2-7","pupils":253},{"urn":139129,"name":"Oasis Academy Blakenhale Junior","type":"Primary","ofstedRating":"Not inspected","postcode":"B33 0XG","ageRange":"7-11","pupils":344},{"urn":148082,"name":"Our Lady's Catholic Primary School","type":"Primary","ofstedRating":"Good","postcode":"B33 0AU","ageRange":"4-11","pupils":202},{"urn":103255,"name":"Sladefield Infant School","type":"Primary","ofstedRating":"Good","postcode":"B8 2TJ","ageRange":"4-7","pupils":297},{"urn":140923,"name":"Smith's Wood Primary Academy","type":"Primary","ofstedRating":"Outstanding","postcode":"B36 0SZ","ageRange":"3-11","pupils":444},{"urn":103470,"name":"St Cuthbert's RC Junior and Infant (NC) School","type":"Primary","ofstedRating":"Good","postcode":"B8 2PS","ageRange":"3-11","pupils":237},{"urn":148093,"name":"St John the Baptist Catholic Primary School","type":"Primary","ofstedRating":"Good","postcode":"B36 0QE","ageRange":"3-11","pupils":202},{"urn":104097,"name":"St Mary and St Margaret's Church of England Aided Primary School","type":"Primary","ofstedRating":"Good","postcode":"B36 9AX","ageRange":"3-11","pupils":236},{"urn":148083,"name":"St Wilfrid's Catholic Junior and Infant School","type":"Primary","ofstedRating":"Good","postcode":"B36 8LY","ageRange":"3-11","pupils":303},{"urn":139011,"name":"Tame Valley Academy","type":"Primary","ofstedRating":"Good","postcode":"B36 8QJ","ageRange":"3-11","pupils":236},{"urn":143087,"name":"The Oval School","type":"Primary","ofstedRating":"Not inspected","postcode":"B33 8JG","ageRange":"3-11","pupils":645},{"urn":138425,"name":"The Shirestone Academy","type":"Primary","ofstedRating":"Outstanding","postcode":"B33 0DH","ageRange":"3-11","pupils":242},{"urn":103268,"name":"Thornton Primary School","type":"Primary","ofstedRating":"Good","postcode":"B8 2LQ","ageRange":"7-11","pupils":477},{"urn":138104,"name":"Timberley Academy","type":"Primary","ofstedRating":"Good","postcode":"B34 7RL","ageRange":"3-11","pupils":606},{"urn":103217,"name":"Ward End Primary School","type":"Primary","ofstedRating":"Good","postcode":"B8 2RA","ageRange":"3-11","pupils":897},{"urn":103132,"name":"Washwood Heath Nursery School","type":"Primary","ofstedRating":"Not inspected","postcode":"B8 2SY","ageRange":"2-5","pupils":111},{"urn":142388,"name":"Cockshut Hill School","type":"Secondary","ofstedRating":"Good","postcode":"B26 2HX","ageRange":"11-18","pupils":954},{"urn":147201,"name":"Eden Girls' Leadership Academy, Birmingham","type":"Secondary","ofstedRating":"Outstanding","postcode":"B10 9HH","ageRange":"11-16","pupils":616},{"urn":103503,"name":"Hodge Hill College","type":"Secondary","ofstedRating":"Good","postcode":"B36 8HB","ageRange":"11-16","pupils":1205},{"urn":103483,"name":"Hodge Hill Girls' School","type":"Secondary","ofstedRating":"Good","postcode":"B36 8EY","ageRange":"11-16","pupils":749},{"urn":136152,"name":"King Edward VI Sheldon Heath Academy","type":"Secondary","ofstedRating":"Good","postcode":"B26 2RZ","ageRange":"11-18","pupils":1192},{"urn":135971,"name":"Park Hall Academy","type":"Secondary","ofstedRating":"Good","postcode":"B36 9HF","ageRange":"11-18","pupils":1270},{"urn":141668,"name":"Saltley Academy","type":"Secondary","ofstedRating":"Good","postcode":"B9 5RX","ageRange":"11-16","pupils":1380},{"urn":143895,"name":"Smith's Wood Academy","type":"Secondary","ofstedRating":"Inadequate","postcode":"B36 0UE","ageRange":"11-16","pupils":744},{"urn":144306,"name":"Tile Cross Academy","type":"Secondary","ofstedRating":"Good","postcode":"B33 9UF","ageRange":"11-16","pupils":624},{"urn":139888,"name":"Washwood Heath Academy","type":"Secondary","ofstedRating":"Good","postcode":"B8 2AS","ageRange":"4-18","pupils":1706},{"urn":142219,"name":"Waverley School","type":"Secondary","ofstedRating":"Good","postcode":"B9 5QA","ageRange":"4-19","pupils":1696},{"urn":139788,"name":"Waverley Studio College","type":"Secondary","ofstedRating":"Good","postcode":"B9 5SX","ageRange":"14-19","pupils":251},{"urn":103627,"name":"Beaufort School","type":"Special","ofstedRating":"Inadequate","postcode":"B34 6BJ","ageRange":"3-11","pupils":92},{"urn":103611,"name":"Braidwood School for the Deaf","type":"Special","ofstedRating":"Not inspected","postcode":"B36 8AF","ageRange":"11-19","pupils":92},{"urn":141171,"name":"Castlewood School","type":"Special","ofstedRating":"Requires Improvement","postcode":"B36 9LF","ageRange":"4-16","pupils":99},{"urn":104132,"name":"Forest Oak School","type":"Special","ofstedRating":"Outstanding","postcode":"B36 0UE","ageRange":"4-19","pupils":193},{"urn":144336,"name":"Hallmoor School","type":"Special","ofstedRating":"Good","postcode":"B33 0DL","ageRange":"4-19","pupils":294},{"urn":148722,"name":"Kitts Green Academy","type":"Special","ofstedRating":"Inadequate","postcode":"B33 9QY","ageRange":"5-14","pupils":58},{"urn":148653,"name":"Leycroft Academy","type":"Special","ofstedRating":"Requires Improvement","postcode":"B33 9UE","ageRange":"4-11","pupils":171},{"urn":104133,"name":"Merstone School","type":"Special","ofstedRating":"Outstanding","postcode":"B36 0UE","ageRange":"2-19","pupils":171},{"urn":149753,"name":"The Heights Academy","type":"Special","ofstedRating":"Not inspected","postcode":"B36 0DD","ageRange":"7-16","pupils":49}]}