{"source":"Ofsted state-funded schools management information (Apr 2026)","sourceUrl":"https://www.gov.uk/government/statistical-data-sets/monthly-management-information-ofsteds-school-inspections-outcomes","schools":[{"urn":107728,"name":"Battyeford CofE (VC) Primary School","type":"Primary","ofstedRating":"Good","postcode":"WF14 9QH","ageRange":"3-11","pupils":428},{"urn":107730,"name":"Birkenshaw Church of England Voluntary Controlled Primary School","type":"Primary","ofstedRating":"Good","postcode":"BD11 2JE","ageRange":"3-11","pupils":462},{"urn":139356,"name":"Birstall Primary Academy","type":"Primary","ofstedRating":"Good","postcode":"WF17 9EE","ageRange":"4-11","pupils":185},{"urn":147534,"name":"Co-op Academy Smithies Moor","type":"Primary","ofstedRating":"Requires Improvement","postcode":"WF16 9BB","ageRange":"3-11","pupils":179},{"urn":107697,"name":"Crossley Fields Junior and Infant School","type":"Primary","ofstedRating":"Good","postcode":"WF14 0BE","ageRange":"4-11","pupils":516},{"urn":107725,"name":"Crowlees Church of England Voluntary Controlled Junior and Infant School","type":"Primary","ofstedRating":"Outstanding","postcode":"WF14 9PD","ageRange":"4-11","pupils":420},{"urn":107719,"name":"East Bierley Church of England Voluntary Controlled Primary School","type":"Primary","ofstedRating":"Requires Improvement","postcode":"BD4 6PH","ageRange":"4-11","pupils":207},{"urn":139357,"name":"Fieldhead Primary Academy","type":"Primary","ofstedRating":"Good","postcode":"WF17 9BX","ageRange":"3-11","pupils":183},{"urn":107666,"name":"Gomersal Primary School","type":"Primary","ofstedRating":"Good","postcode":"BD19 4PX","ageRange":"4-11","pupils":405},{"urn":107747,"name":"Gomersal St Mary's Church of England Voluntary Controlled Primary School","type":"Primary","ofstedRating":"Good","postcode":"BD19 4NA","ageRange":"3-11","pupils":166},{"urn":107667,"name":"Hartshead Junior and Infant School","type":"Primary","ofstedRating":"Good","postcode":"WF15 8AW","ageRange":"4-11","pupils":83},{"urn":107723,"name":"Headlands Church of England Voluntary Controlled Junior, Infant and Nursery School","type":"Primary","ofstedRating":"Not inspected","postcode":"WF15 6PR","ageRange":"3-11","pupils":335},{"urn":141904,"name":"Heaton Avenue, A Share Primary Academy","type":"Primary","ofstedRating":"Requires Improvement","postcode":"BD19 3AE","ageRange":"3-11","pupils":361},{"urn":150366,"name":"Heckmondwike Primary Academy","type":"Primary","ofstedRating":"Inadequate","postcode":"WF16 0AN","ageRange":"3-11","pupils":435},{"urn":107684,"name":"High Bank Junior Infant and Nursery School","type":"Primary","ofstedRating":"Not inspected","postcode":"WF15 8LD","ageRange":"3-11","pupils":134},{"urn":107669,"name":"Hightown Junior Infant & Nursery School","type":"Primary","ofstedRating":"Good","postcode":"WF15 8BL","ageRange":"3-11","pupils":198},{"urn":148849,"name":"Holy Spirit Catholic Primary Academy","type":"Primary","ofstedRating":"Good","postcode":"WF16 9EA","ageRange":"4-11","pupils":208},{"urn":107665,"name":"Hopton Primary School","type":"Primary","ofstedRating":"Good","postcode":"WF14 8PR","ageRange":"3-11","pupils":321},{"urn":107671,"name":"Howard Park Community School","type":"Primary","ofstedRating":"Good","postcode":"BD19 3SA","ageRange":"3-11","pupils":235},{"urn":148293,"name":"Kirkheaton Primary School","type":"Primary","ofstedRating":"Good","postcode":"HD5 0HR","ageRange":"3-11","pupils":351},{"urn":107670,"name":"Littletown Junior Infant and Nursery School","type":"Primary","ofstedRating":"Good","postcode":"WF15 6LP","ageRange":"3-11","pupils":169},{"urn":141688,"name":"Millbridge, A Share Primary Academy","type":"Primary","ofstedRating":"Good","postcode":"WF15 6HU","ageRange":"3-11","pupils":288},{"urn":107685,"name":"Norristhorpe Junior and Infant School","type":"Primary","ofstedRating":"Good","postcode":"WF15 7AW","ageRange":"4-11","pupils":423},{"urn":147884,"name":"Old Bank Academy","type":"Primary","ofstedRating":"Good","postcode":"WF14 0HW","ageRange":"3-11","pupils":106},{"urn":152304,"name":"Roberttown CofE Primary School","type":"Primary","ofstedRating":"Good","postcode":"WF15 8BE","ageRange":"4-11","pupils":233},{"urn":107674,"name":"Scholes Village Primary School","type":"Primary","ofstedRating":"Not inspected","postcode":"BD19 6DN","ageRange":"3-11","pupils":221},{"urn":148863,"name":"St Patrick's Catholic Primary Academy","type":"Primary","ofstedRating":"Good","postcode":"WF17 9LQ","ageRange":"3-11","pupils":243},{"urn":107737,"name":"St Peter's Church of England Voluntary Aided Junior, Infant and Early Years School","type":"Primary","ofstedRating":"Good","postcode":"WF17 9HN","ageRange":"3-11","pupils":206},{"urn":136511,"name":"Whitechapel Church of England Primary School","type":"Primary","ofstedRating":"Good","postcode":"BD19 6HR","ageRange":"4-11","pupils":412},{"urn":138111,"name":"BBG Academy","type":"Secondary","ofstedRating":"Good","postcode":"BD19 4BE","ageRange":"11-16","pupils":1046},{"urn":137424,"name":"Batley Girls' High School","type":"Secondary","ofstedRating":"Not inspected","postcode":"WF17 0LD","ageRange":"11-19","pupils":1371},{"urn":146367,"name":"Castle Hall Academy","type":"Secondary","ofstedRating":"Good","postcode":"WF14 9PH","ageRange":"11-16","pupils":829},{"urn":136283,"name":"Heckmondwike Grammar School","type":"Secondary","ofstedRating":"Good","postcode":"WF16 0AH","ageRange":"11-18","pupils":1468},{"urn":107778,"name":"Spen Valley High School","type":"Secondary","ofstedRating":"Good","postcode":"WF15 7LX","ageRange":"11-16","pupils":960},{"urn":136674,"name":"The Mirfield Free Grammar","type":"Secondary","ofstedRating":"Good","postcode":"WF14 9EZ","ageRange":"11-18","pupils":1323},{"urn":149162,"name":"Whitcliffe Mount, A Share Academy","type":"Secondary","ofstedRating":"Not inspected","postcode":"BD19 3AQ","ageRange":"11-16","pupils":1244},{"urn":107802,"name":"Fairfield School","type":"Special","ofstedRating":"Good","postcode":"WF17 8AS","ageRange":"3-19","pupils":136},{"urn":107796,"name":"Hollybank School","type":"Special","ofstedRating":"Outstanding","postcode":"WF14 0DQ","ageRange":"2-19","pupils":37}]}