{"source":"Ofsted state-funded schools management information (Apr 2026)","sourceUrl":"https://www.gov.uk/government/statistical-data-sets/monthly-management-information-ofsteds-school-inspections-outcomes","schools":[{"urn":146086,"name":"All Saints Church of England Primary School, Newmarket","type":"Primary","ofstedRating":"Good","postcode":"CB8 8JE","ageRange":"4-11","pupils":192},{"urn":124690,"name":"Barrow Church of England Voluntary Controlled Primary School","type":"Primary","ofstedRating":"Not inspected","postcode":"IP29 5AU","ageRange":"4-11","pupils":207},{"urn":144275,"name":"Beck Row Primary Academy","type":"Primary","ofstedRating":"Good","postcode":"IP28 8AE","ageRange":"4-11","pupils":243},{"urn":141546,"name":"Burton End Primary Academy","type":"Primary","ofstedRating":"Good","postcode":"CB9 9DE","ageRange":"3-11","pupils":446},{"urn":151639,"name":"Cavendish Church of England Primary School","type":"Primary","ofstedRating":"Inadequate","postcode":"CO10 8BA","ageRange":"4-11","pupils":60},{"urn":144399,"name":"Clare Community Primary School","type":"Primary","ofstedRating":"Good","postcode":"CO10 8PZ","ageRange":"4-11","pupils":201},{"urn":144276,"name":"Clements Primary Academy","type":"Primary","ofstedRating":"Good","postcode":"CB9 8NJ","ageRange":"2-11","pupils":262},{"urn":141371,"name":"Coupals Primary Academy","type":"Primary","ofstedRating":"Good","postcode":"CB9 0LB","ageRange":"4-11","pupils":287},{"urn":139149,"name":"Elveden Church of England Primary Academy","type":"Primary","ofstedRating":"Outstanding","postcode":"IP24 3TN","ageRange":"4-11","pupils":101},{"urn":151104,"name":"Exning Primary School","type":"Primary","ofstedRating":"Outstanding","postcode":"CB8 7EW","ageRange":"5-11","pupils":229},{"urn":136316,"name":"Forest Academy","type":"Primary","ofstedRating":"Good","postcode":"IP27 0FP","ageRange":"3-11","pupils":412},{"urn":145476,"name":"Glade Academy","type":"Primary","ofstedRating":"Good","postcode":"IP27 0DA","ageRange":"4-11","pupils":189},{"urn":142027,"name":"Great Heath Academy","type":"Primary","ofstedRating":"Good","postcode":"IP28 7PT","ageRange":"3-11","pupils":469},{"urn":147450,"name":"Great Whelnetham Church of England Primary School","type":"Primary","ofstedRating":"Good","postcode":"IP30 0UA","ageRange":"5-11","pupils":85},{"urn":143861,"name":"Houldsworth Valley Primary Academy","type":"Primary","ofstedRating":"Good","postcode":"CB8 0PU","ageRange":"4-11","pupils":336},{"urn":124538,"name":"Hundon Community Primary School","type":"Primary","ofstedRating":"Good","postcode":"CO10 8EE","ageRange":"4-11","pupils":70},{"urn":151388,"name":"Ickworth Park Primary School","type":"Primary","ofstedRating":"Good","postcode":"IP29 5SB","ageRange":"5-11","pupils":197},{"urn":139485,"name":"Kedington Primary Academy","type":"Primary","ofstedRating":"Good","postcode":"CB9 7QZ","ageRange":"4-11","pupils":214},{"urn":124539,"name":"Lakenheath Community Primary School","type":"Primary","ofstedRating":"Good","postcode":"IP27 9DU","ageRange":"4-11","pupils":260},{"urn":142993,"name":"Laureate Community Academy","type":"Primary","ofstedRating":"Not inspected","postcode":"CB8 0AN","ageRange":"2-11","pupils":241},{"urn":124709,"name":"Moulton Church of England Voluntary Controlled Primary School","type":"Primary","ofstedRating":"Outstanding","postcode":"CB8 8PR","ageRange":"4-11","pupils":210},{"urn":124537,"name":"New Cangle Community Primary School","type":"Primary","ofstedRating":"Good","postcode":"CB9 0DU","ageRange":"4-11","pupils":210},{"urn":124565,"name":"Paddocks Primary School","type":"Primary","ofstedRating":"Good","postcode":"CB8 0DL","ageRange":"4-11","pupils":185},{"urn":138161,"name":"Place Farm Primary Academy","type":"Primary","ofstedRating":"Good","postcode":"CB9 8HF","ageRange":"3-11","pupils":403},{"urn":124712,"name":"Risby Church of England Voluntary Controlled Primary School","type":"Primary","ofstedRating":"Good","postcode":"IP28 6RT","ageRange":"4-11","pupils":202},{"urn":142025,"name":"St Christopher's CEVCP School","type":"Primary","ofstedRating":"Good","postcode":"IP28 8XQ","ageRange":"3-11","pupils":340},{"urn":143624,"name":"St Felix Roman Catholic Primary School, Haverhill","type":"Primary","ofstedRating":"Good","postcode":"CB9 9DE","ageRange":"3-11","pupils":217},{"urn":139448,"name":"St Louis Catholic Academy","type":"Primary","ofstedRating":"Good","postcode":"CB8 7AA","ageRange":"3-11","pupils":295},{"urn":137419,"name":"St Mary's Church of England Academy","type":"Primary","ofstedRating":"Requires Improvement","postcode":"IP28 7LR","ageRange":"4-11","pupils":405},{"urn":145031,"name":"The Pines Primary School","type":"Primary","ofstedRating":"Good","postcode":"IP28 8WL","ageRange":"3-11","pupils":244},{"urn":124698,"name":"Thurlow Voluntary Controlled Primary School","type":"Primary","ofstedRating":"Good","postcode":"CB9 7HY","ageRange":"4-11","pupils":78},{"urn":150276,"name":"West Row Academy","type":"Primary","ofstedRating":"Requires Improvement","postcode":"IP28 8NY","ageRange":"4-11","pupils":195},{"urn":140044,"name":"Westfield Primary Academy","type":"Primary","ofstedRating":"Good","postcode":"CB9 0BW","ageRange":"3-11","pupils":440},{"urn":142995,"name":"Wickhambrook Primary Academy","type":"Primary","ofstedRating":"Not inspected","postcode":"CB8 8XN","ageRange":"4-11","pupils":176},{"urn":138250,"name":"Breckland School","type":"Secondary","ofstedRating":"Good","postcode":"IP27 0PE","ageRange":"11-16","pupils":613},{"urn":138162,"name":"Castle Manor Academy","type":"Secondary","ofstedRating":"Not inspected","postcode":"CB9 9JE","ageRange":"11-16","pupils":757},{"urn":139867,"name":"Mildenhall College Academy","type":"Secondary","ofstedRating":"Good","postcode":"IP28 7JX","ageRange":"11-18","pupils":1338},{"urn":140669,"name":"Newmarket Academy","type":"Secondary","ofstedRating":"Good","postcode":"CB8 0EB","ageRange":"11-16","pupils":813},{"urn":136322,"name":"Samuel Ward Academy","type":"Secondary","ofstedRating":"Good","postcode":"CB9 0LD","ageRange":"11-18","pupils":1152},{"urn":136757,"name":"Stour Valley Community School","type":"Secondary","ofstedRating":"Good","postcode":"CO10 8PJ","ageRange":"11-16","pupils":569},{"urn":139732,"name":"Churchill Special Free School","type":"Special","ofstedRating":"Not inspected","postcode":"CB9 0LB","ageRange":"8-18","pupils":71}]}