{"source":"Ofsted state-funded schools management information (Apr 2026)","sourceUrl":"https://www.gov.uk/government/statistical-data-sets/monthly-management-information-ofsteds-school-inspections-outcomes","schools":[{"urn":105325,"name":"All Saints Church of England Primary School, Stand","type":"Primary","ofstedRating":"Good","postcode":"M45 8PL","ageRange":"3-11","pupils":231},{"urn":149819,"name":"Brentnall Academy","type":"Primary","ofstedRating":"Inadequate","postcode":"M7 4RP","ageRange":"3-11","pupils":196},{"urn":138543,"name":"Broughton Jewish Cassel Fox Primary School","type":"Primary","ofstedRating":"Good","postcode":"M7 4RT","ageRange":"3-11","pupils":332},{"urn":105352,"name":"Bury and Whitefield Jewish Primary School","type":"Primary","ofstedRating":"Good","postcode":"BL9 8JT","ageRange":"3-11","pupils":102},{"urn":150485,"name":"Butterstile Primary School","type":"Primary","ofstedRating":"Good","postcode":"M25 9RJ","ageRange":"3-11","pupils":395},{"urn":150486,"name":"Cams Lane Primary School","type":"Primary","ofstedRating":"Good","postcode":"M26 3SW","ageRange":"4-11","pupils":200},{"urn":105313,"name":"Chapelfield Primary School","type":"Primary","ofstedRating":"Good","postcode":"M26 1LH","ageRange":"3-11","pupils":292},{"urn":141673,"name":"Gorsefield Primary School","type":"Primary","ofstedRating":"Good","postcode":"M26 4DW","ageRange":"2-11","pupils":336},{"urn":150484,"name":"Heaton Park Primary School","type":"Primary","ofstedRating":"Good","postcode":"M45 6TE","ageRange":"3-11","pupils":418},{"urn":144575,"name":"Higher Lane Primary School","type":"Primary","ofstedRating":"Good","postcode":"M45 7EX","ageRange":"3-11","pupils":512},{"urn":105314,"name":"Hollins Grundy Primary School","type":"Primary","ofstedRating":"Good","postcode":"BL9 8AY","ageRange":"4-11","pupils":205},{"urn":105886,"name":"Lower Kersal Community Primary School","type":"Primary","ofstedRating":"Good","postcode":"M7 3TN","ageRange":"3-11","pupils":249},{"urn":105299,"name":"Mersey Drive Community Primary School","type":"Primary","ofstedRating":"Good","postcode":"M45 8LN","ageRange":"3-11","pupils":196},{"urn":105345,"name":"Our Lady of Grace RC Primary School","type":"Primary","ofstedRating":"Good","postcode":"M25 3AS","ageRange":"3-11","pupils":284},{"urn":149934,"name":"Park View Primary School","type":"Primary","ofstedRating":"Good","postcode":"M25 1FA","ageRange":"3-11","pupils":436},{"urn":147159,"name":"Radcliffe Hall Church of England Methodist Primary School","type":"Primary","ofstedRating":"Good","postcode":"M26 2GB","ageRange":"3-11","pupils":296},{"urn":150488,"name":"Ribble Drive Community Primary School","type":"Primary","ofstedRating":"Good","postcode":"M45 8TD","ageRange":"4-11","pupils":187},{"urn":151518,"name":"Sedgley Park Community Primary School","type":"Primary","ofstedRating":"Good","postcode":"M25 0HT","ageRange":"3-11","pupils":260},{"urn":150560,"name":"St Bernadette's Roman Catholic Primary School, a Voluntary Academy","type":"Primary","ofstedRating":"Good","postcode":"M45 8PT","ageRange":"3-11","pupils":334},{"urn":105351,"name":"St Hilda's Church of England Primary School","type":"Primary","ofstedRating":"Good","postcode":"M25 1HA","ageRange":"4-11","pupils":183},{"urn":145560,"name":"St John's Church of England Primary School, Radcliffe","type":"Primary","ofstedRating":"Good","postcode":"M26 1AW","ageRange":"3-11","pupils":208},{"urn":105323,"name":"St Margaret's Church of England Primary School","type":"Primary","ofstedRating":"Not inspected","postcode":"M25 2BW","ageRange":"4-11","pupils":223},{"urn":105342,"name":"St Mary's Church of England Aided Primary School, Prestwich","type":"Primary","ofstedRating":"Not inspected","postcode":"M25 1BP","ageRange":"3-11","pupils":229},{"urn":150561,"name":"St Mary's Roman Catholic Primary School, A Voluntary Academy","type":"Primary","ofstedRating":"Good","postcode":"M26 4DG","ageRange":"3-11","pupils":348},{"urn":149679,"name":"St Michael's Roman Catholic Primary School, A Voluntary Academy","type":"Primary","ofstedRating":"Inadequate","postcode":"M45 8NJ","ageRange":"3-11","pupils":209},{"urn":105928,"name":"St Paul's CofE Primary School","type":"Primary","ofstedRating":"Good","postcode":"M7 3PT","ageRange":"3-11","pupils":200},{"urn":105968,"name":"St Philip's RC Primary School","type":"Primary","ofstedRating":"Outstanding","postcode":"M7 4WP","ageRange":"3-11","pupils":362},{"urn":144593,"name":"Sunny Bank Primary School","type":"Primary","ofstedRating":"Good","postcode":"BL9 8EQ","ageRange":"5-11","pupils":216},{"urn":146932,"name":"Unsworth Primary School","type":"Primary","ofstedRating":"Good","postcode":"BL9 8LY","ageRange":"3-11","pupils":214},{"urn":150487,"name":"Whitefield Community Primary School","type":"Primary","ofstedRating":"Good","postcode":"M45 6DP","ageRange":"3-11","pupils":190},{"urn":136661,"name":"Yesoiday Hatorah Boys Academy","type":"Primary","ofstedRating":"Good","postcode":"M25 0JW","ageRange":"3-11","pupils":438},{"urn":147227,"name":"Yesoiday Hatorah Girls Academy","type":"Primary","ofstedRating":"Outstanding","postcode":"M25 0JW","ageRange":"3-11","pupils":450},{"urn":138698,"name":"Beis Yaakov High School","type":"Secondary","ofstedRating":"Not inspected","postcode":"M7 4FF","ageRange":"11-16","pupils":285},{"urn":134195,"name":"Manchester Mesivta School","type":"Secondary","ofstedRating":"Requires Improvement","postcode":"M25 0PH","ageRange":"11-18","pupils":241},{"urn":151969,"name":"Parrenthorn High School","type":"Secondary","ofstedRating":"Good","postcode":"M25 2BW","ageRange":"11-16","pupils":1033},{"urn":151027,"name":"Philips High School","type":"Secondary","ofstedRating":"Requires Improvement","postcode":"M45 7PH","ageRange":"11-16","pupils":872},{"urn":148050,"name":"St Monica's RC High School, a Voluntary Academy","type":"Secondary","ofstedRating":"Not inspected","postcode":"M25 1JH","ageRange":"11-16","pupils":1066},{"urn":150715,"name":"Star Radcliffe Academy","type":"Secondary","ofstedRating":"Not inspected","postcode":"M26 2SZ","ageRange":"11-16","pupils":149},{"urn":147883,"name":"The Heys School","type":"Secondary","ofstedRating":"Good","postcode":"M25 1JZ","ageRange":"11-16","pupils":569},{"urn":143848,"name":"Unsworth Academy","type":"Secondary","ofstedRating":"Good","postcode":"BL9 8LP","ageRange":"11-16","pupils":968},{"urn":150236,"name":"Brookhaven School","type":"Special","ofstedRating":"Not inspected","postcode":"BL9 8LP","ageRange":"11-16","pupils":50},{"urn":105376,"name":"Cloughside College","type":"Special","ofstedRating":"Good","postcode":"M25 3BL","ageRange":"11-19","pupils":16},{"urn":146891,"name":"Elms Bank","type":"Special","ofstedRating":"Outstanding","postcode":"M45 8PJ","ageRange":"11-19","pupils":344},{"urn":105377,"name":"Millwood Primary Special School","type":"Special","ofstedRating":"Outstanding","postcode":"M26 3BW","ageRange":"2-11","pupils":174}]}