{"source":"Ofsted state-funded schools management information (Apr 2026)","sourceUrl":"https://www.gov.uk/government/statistical-data-sets/monthly-management-information-ofsteds-school-inspections-outcomes","schools":[{"urn":143440,"name":"Babraham CofE (VC) Primary School","type":"Primary","ofstedRating":"Not inspected","postcode":"CB22 3AG","ageRange":"5-11","pupils":99},{"urn":110781,"name":"Barrington CofE VC Primary School","type":"Primary","ofstedRating":"Good","postcode":"CB22 7RG","ageRange":"4-11","pupils":165},{"urn":110829,"name":"Barton CofE VA Primary School","type":"Primary","ofstedRating":"Not inspected","postcode":"CB23 7BD","ageRange":"4-11","pupils":121},{"urn":110602,"name":"Bassingbourn Primary School","type":"Primary","ofstedRating":"Not inspected","postcode":"SG8 5NP","ageRange":"5-11","pupils":365},{"urn":110746,"name":"Bewick Bridge Community Primary School","type":"Primary","ofstedRating":"Good","postcode":"CB1 9ND","ageRange":"4-11","pupils":218},{"urn":110784,"name":"Castle Camps Church of England (Controlled) Primary School","type":"Primary","ofstedRating":"Not inspected","postcode":"CB21 4TH","ageRange":"3-11","pupils":123},{"urn":110801,"name":"Cherry Hinton Church of England Voluntary Controlled Primary School","type":"Primary","ofstedRating":"Good","postcode":"CB1 9HH","ageRange":"3-11","pupils":183},{"urn":110665,"name":"Colville Primary School","type":"Primary","ofstedRating":"Not inspected","postcode":"CB1 9EJ","ageRange":"3-11","pupils":228},{"urn":110786,"name":"Coton Church of England (Voluntary Controlled) Primary School","type":"Primary","ofstedRating":"Requires Improvement","postcode":"CB23 7PW","ageRange":"4-11","pupils":107},{"urn":110798,"name":"Duxford Church of England Community Primary School","type":"Primary","ofstedRating":"Good","postcode":"CB22 4RA","ageRange":"4-11","pupils":158},{"urn":145423,"name":"Fen Ditton Primary School","type":"Primary","ofstedRating":"Good","postcode":"CB5 8SZ","ageRange":"4-11","pupils":136},{"urn":110607,"name":"Fowlmere Primary School","type":"Primary","ofstedRating":"Good","postcode":"SG8 7SL","ageRange":"4-11","pupils":77},{"urn":110608,"name":"Foxton Primary School","type":"Primary","ofstedRating":"Good","postcode":"CB22 6RN","ageRange":"5-11","pupils":76},{"urn":110759,"name":"Fulbourn Primary School","type":"Primary","ofstedRating":"Good","postcode":"CB21 5BH","ageRange":"4-11","pupils":264},{"urn":142638,"name":"Gamlingay Village Primary","type":"Primary","ofstedRating":"Good","postcode":"SG19 3HD","ageRange":"3-11","pupils":395},{"urn":110611,"name":"Great Abington Primary School","type":"Primary","ofstedRating":"Good","postcode":"CB21 6AE","ageRange":"4-11","pupils":130},{"urn":150022,"name":"Great Wilbraham CofE Primary Academy","type":"Primary","ofstedRating":"Inadequate","postcode":"CB21 5JQ","ageRange":"3-11","pupils":86},{"urn":110831,"name":"Great and Little Shelford CofE (Aided) Primary School","type":"Primary","ofstedRating":"Good","postcode":"CB22 5EL","ageRange":"4-11","pupils":206},{"urn":142811,"name":"Guilden Morden CofE Primary Academy","type":"Primary","ofstedRating":"Good","postcode":"SG8 0JZ","ageRange":"2-11","pupils":59},{"urn":110748,"name":"Hardwick and Cambourne Community Primary School","type":"Primary","ofstedRating":"Good","postcode":"CB23 7RE","ageRange":"4-11","pupils":570},{"urn":151048,"name":"Harston and Newton Primary School","type":"Primary","ofstedRating":"Good","postcode":"CB22 7PX","ageRange":"4-11","pupils":117},{"urn":110796,"name":"Haslingfield Endowed Primary School","type":"Primary","ofstedRating":"Good","postcode":"CB23 1JW","ageRange":"4-11","pupils":140},{"urn":110673,"name":"Hauxton Primary School","type":"Primary","ofstedRating":"Good","postcode":"CB22 5HY","ageRange":"4-11","pupils":75},{"urn":110594,"name":"Homerton Early Years Centre","type":"Primary","ofstedRating":"Outstanding","postcode":"CB1 7ST","ageRange":"2-5","pupils":103},{"urn":110832,"name":"Linton CofE Infant School","type":"Primary","ofstedRating":"Good","postcode":"CB21 4JX","ageRange":"5-7","pupils":161},{"urn":143576,"name":"Linton Heights Junior School","type":"Primary","ofstedRating":"Not inspected","postcode":"CB21 4XB","ageRange":"7-11","pupils":233},{"urn":149098,"name":"Marleigh Primary Academy","type":"Primary","ofstedRating":"Not inspected","postcode":"CB5 8BG","ageRange":"3-11","pupils":150},{"urn":140622,"name":"Meadow Primary School","type":"Primary","ofstedRating":"Good","postcode":"CB21 4DJ","ageRange":"3-11","pupils":207},{"urn":110614,"name":"Melbourn Primary School","type":"Primary","ofstedRating":"Good","postcode":"SG8 6DB","ageRange":"4-11","pupils":376},{"urn":110615,"name":"Meldreth Primary School","type":"Primary","ofstedRating":"Not inspected","postcode":"SG8 6LA","ageRange":"4-11","pupils":191},{"urn":110626,"name":"Meridian Primary School","type":"Primary","ofstedRating":"Good","postcode":"CB23 7DD","ageRange":"4-11","pupils":190},{"urn":110657,"name":"Morley Memorial Primary School","type":"Primary","ofstedRating":"Good","postcode":"CB1 7TX","ageRange":"4-11","pupils":381},{"urn":110836,"name":"Petersfield CofE Aided Primary School","type":"Primary","ofstedRating":"Good","postcode":"SG8 5QG","ageRange":"4-11","pupils":134},{"urn":110763,"name":"Queen Edith Primary School","type":"Primary","ofstedRating":"Good","postcode":"CB1 8QP","ageRange":"4-11","pupils":403},{"urn":136241,"name":"Queen Emma Primary School","type":"Primary","ofstedRating":"Good","postcode":"CB1 8QY","ageRange":"4-11","pupils":405},{"urn":145424,"name":"Stapleford Community Primary School","type":"Primary","ofstedRating":"Good","postcode":"CB22 5BJ","ageRange":"2-11","pupils":210},{"urn":110793,"name":"Steeple Morden CofE VC Primary School","type":"Primary","ofstedRating":"Requires Improvement","postcode":"SG8 0PD","ageRange":"4-11","pupils":148},{"urn":110834,"name":"Teversham CofE VA Primary School","type":"Primary","ofstedRating":"Good","postcode":"CB1 9AZ","ageRange":"4-11","pupils":173},{"urn":135132,"name":"The Bellbird Primary School","type":"Primary","ofstedRating":"Good","postcode":"CB22 3GB","ageRange":"4-11","pupils":410},{"urn":148454,"name":"The Icknield Primary School","type":"Primary","ofstedRating":"Good","postcode":"CB22 3EA","ageRange":"2-11","pupils":196},{"urn":110765,"name":"The Spinney Primary School","type":"Primary","ofstedRating":"Requires Improvement","postcode":"CB1 9PB","ageRange":"4-11","pupils":187},{"urn":145246,"name":"Thriplow CofE Primary School","type":"Primary","ofstedRating":"Good","postcode":"SG8 7RH","ageRange":"4-11","pupils":99},{"urn":136802,"name":"Trumpington Meadows Primary School","type":"Primary","ofstedRating":"Good","postcode":"CB2 9AY","ageRange":"4-11","pupils":250},{"urn":110795,"name":"William Westley Church of England VC Primary School","type":"Primary","ofstedRating":"Not inspected","postcode":"CB22 4NE","ageRange":"4-11","pupils":185},{"urn":137427,"name":"Bassingbourn Village College","type":"Secondary","ofstedRating":"Good","postcode":"SG8 5NJ","ageRange":"11-16","pupils":658},{"urn":140265,"name":"Cambridge Academy for Science and Technology","type":"Secondary","ofstedRating":"Good","postcode":"CB2 0SZ","ageRange":"13-19","pupils":455},{"urn":136463,"name":"Comberton Village College","type":"Secondary","ofstedRating":"Not inspected","postcode":"CB23 7DU","ageRange":"11-18","pupils":1962},{"urn":136442,"name":"Linton Village College","type":"Secondary","ofstedRating":"Good","postcode":"CB21 4JB","ageRange":"11-16","pupils":803},{"urn":137527,"name":"Melbourn Village College","type":"Secondary","ofstedRating":"Not inspected","postcode":"SG8 6EF","ageRange":"11-16","pupils":585},{"urn":136775,"name":"Sawston Village College","type":"Secondary","ofstedRating":"Good","postcode":"CB22 3BP","ageRange":"11-16","pupils":1194},{"urn":142035,"name":"The Netherhall School","type":"Secondary","ofstedRating":"Good","postcode":"CB1 8NN","ageRange":"11-18","pupils":1266},{"urn":134937,"name":"Granta School","type":"Special","ofstedRating":"Requires Improvement","postcode":"CB21 4NN","ageRange":"2-19","pupils":182},{"urn":134765,"name":"Pilgrim Pathways School","type":"Special","ofstedRating":"Outstanding","postcode":"CB21 5EE","ageRange":"5-18","pupils":2}]}