{"source":"Ofsted state-funded schools management information (Apr 2026)","sourceUrl":"https://www.gov.uk/government/statistical-data-sets/monthly-management-information-ofsteds-school-inspections-outcomes","schools":[{"urn":101787,"name":"All Saints CofE Primary School","type":"Primary","ofstedRating":"Not inspected","postcode":"SE19 3LG","ageRange":"3-11","pupils":207},{"urn":141120,"name":"Beulah Infants' School","type":"Primary","ofstedRating":"Good","postcode":"CR7 8NJ","ageRange":"3-7","pupils":200},{"urn":101712,"name":"Beulah Junior School","type":"Primary","ofstedRating":"Requires Improvement","postcode":"CR7 8JF","ageRange":"7-11","pupils":223},{"urn":144626,"name":"Cypress Primary School","type":"Primary","ofstedRating":"Good","postcode":"SE25 4AU","ageRange":"2-11","pupils":680},{"urn":137195,"name":"David Livingstone Academy","type":"Primary","ofstedRating":"Not inspected","postcode":"CR7 8HX","ageRange":"4-11","pupils":196},{"urn":101778,"name":"Downsview Primary and Nursery School","type":"Primary","ofstedRating":"Good","postcode":"SE19 3XE","ageRange":"3-11","pupils":632},{"urn":100564,"name":"Granton Primary School","type":"Primary","ofstedRating":"Outstanding","postcode":"SW16 5AN","ageRange":"3-11","pupils":652},{"urn":131824,"name":"Hitherfield Primary School","type":"Primary","ofstedRating":"Good","postcode":"SW16 2JQ","ageRange":"3-11","pupils":619},{"urn":100633,"name":"Immanuel and St Andrew Church of England Primary School","type":"Primary","ofstedRating":"Not inspected","postcode":"SW16 5SL","ageRange":"3-11","pupils":417},{"urn":146724,"name":"Kensington Avenue Primary School","type":"Primary","ofstedRating":"Requires Improvement","postcode":"CR7 8BT","ageRange":"4-11","pupils":513},{"urn":101785,"name":"Norbury Manor Primary School","type":"Primary","ofstedRating":"Good","postcode":"SW16 5QR","ageRange":"3-11","pupils":417},{"urn":101783,"name":"Rockmount Primary School","type":"Primary","ofstedRating":"Not inspected","postcode":"SE19 3ST","ageRange":"3-11","pupils":449},{"urn":100632,"name":"St Andrew's Catholic Primary School","type":"Primary","ofstedRating":"Outstanding","postcode":"SW16 2ET","ageRange":"4-11","pupils":397},{"urn":138335,"name":"St Cyprian's Greek Orthodox Primary Academy","type":"Primary","ofstedRating":"Requires Improvement","postcode":"CR7 8DZ","ageRange":"3-11","pupils":275},{"urn":137959,"name":"St James the Great RC Primary and Nursery School","type":"Primary","ofstedRating":"Outstanding","postcode":"CR7 8HJ","ageRange":"3-11","pupils":448},{"urn":101803,"name":"St Joseph's RC Infant School","type":"Primary","ofstedRating":"Good","postcode":"SE19 3NX","ageRange":"3-7","pupils":153},{"urn":101795,"name":"St Joseph's RC Junior School","type":"Primary","ofstedRating":"Not inspected","postcode":"SE19 3NU","ageRange":"7-11","pupils":194},{"urn":145615,"name":"St Leonard's Church of England Primary School","type":"Primary","ofstedRating":"Outstanding","postcode":"SW16 6NP","ageRange":"4-11","pupils":406},{"urn":149556,"name":"Streatham Wells Primary","type":"Primary","ofstedRating":"Outstanding","postcode":"SW2 3NJ","ageRange":"3-11","pupils":234},{"urn":100585,"name":"Sunnyhill Primary School","type":"Primary","ofstedRating":"Good","postcode":"SW16 2UW","ageRange":"3-11","pupils":407},{"urn":131723,"name":"Thornton Heath Nursery School","type":"Primary","ofstedRating":"Good","postcode":"CR7 8RS","ageRange":"2-4","pupils":103},{"urn":100638,"name":"Bishop Thomas Grant Catholic Secondary School","type":"Secondary","ofstedRating":"Not inspected","postcode":"SW16 2HY","ageRange":"11-19","pupils":1179},{"urn":137093,"name":"Dunraven School","type":"Secondary","ofstedRating":"Good","postcode":"SW16 2QB","ageRange":"4-18","pupils":1789},{"urn":150055,"name":"Harris Academy Beulah Hill","type":"Secondary","ofstedRating":"Not inspected","postcode":"SE19 3UG","ageRange":"11-19","pupils":1029},{"urn":135311,"name":"Harris City Academy Crystal Palace","type":"Secondary","ofstedRating":"Not inspected","postcode":"SE19 2JH","ageRange":"11-18","pupils":1162},{"urn":137754,"name":"Norbury High School for Girls","type":"Secondary","ofstedRating":"Good","postcode":"CR7 8BT","ageRange":"11-19","pupils":1173},{"urn":138221,"name":"St Joseph's College","type":"Secondary","ofstedRating":"Good","postcode":"SE19 3HL","ageRange":"11-18","pupils":807},{"urn":100590,"name":"Woodmansterne School","type":"Secondary","ofstedRating":"Not inspected","postcode":"SW16 5UQ","ageRange":"3-18","pupils":1621},{"urn":101856,"name":"Priory School","type":"Special","ofstedRating":"Good","postcode":"SE19 3QN","ageRange":"11-19","pupils":138},{"urn":133440,"name":"The Livity School","type":"Special","ofstedRating":"Not inspected","postcode":"SW16 2PW","ageRange":"2-11","pupils":127}]}